pynput_json_manager/__init__.py
pynput_json_manager/manage_jsons.py
pynput_json_manager/manager/__init__.py
pynput_json_manager/manager/delete_parameter.py
pynput_json_manager/manager/experimental_reset.py
pynput_json_manager/manager/experiments_removal.py
pynput_json_manager/manager/fancy_exp_summary.py
pynput_json_manager/manager/gpuhandler.py
pynput_json_manager/manager/parameter_shorcut.py
pynput_json_manager/manager/parameters_information.py
pynput_json_manager/manager/results_reader.py
pynput_json_manager/manager/setup_fancy_generator.py
pynput_json_manager/manager/setup_generator.py
pynput_json_manager/manager/setup_reader.py
pynput_json_manager/manager/update_parameters.py
pynput_json_manager/utils/__init__.py
pynput_json_manager/utils/clear.py
pynput_json_manager/utils/get_logger.py
pynput_json_manager/utils/packages.py
pynput_json_manager/utils/setup_folders.py
pynput_json_manager-0.0.7.dist-info/LICENSE
pynput_json_manager-0.0.7.dist-info/METADATA
pynput_json_manager-0.0.7.dist-info/WHEEL
pynput_json_manager-0.0.7.dist-info/top_level.txt
pynput_json_manager-0.0.7.dist-info/RECORD
