Metadata-Version: 2.1
Name: pynput-json-manager
Version: 0.0.7
Summary: handles jsons creation and management
Home-page: https://gitlab.com/ey_datakalab/json_manager
Author: Edouard Yvinec
Author-email: Edouard Yvinec <edouardyvinec@hotmail.fr>
License: MIT License
Project-URL: Homepage, https://gitlab.com/ey_datakalab/json_manager
Classifier: Programming Language :: Python :: 3
Requires-Python: >=3.9
License-File: LICENSE
